pyzip/__init__.py
pyzip/tests/__init__.py
pyzip/tests/test_pyzip.py
pyzip-0.3.0.dist-info/AUTHORS
pyzip-0.3.0.dist-info/LICENSE
pyzip-0.3.0.dist-info/METADATA
pyzip-0.3.0.dist-info/WHEEL
pyzip-0.3.0.dist-info/top_level.txt
pyzip-0.3.0.dist-info/RECORD
