Metadata-Version: 2.1
Name: pyzip
Version: 0.3.0
Summary: PyZip is a package for handling zip-in-memory content as a dictionary.
Home-page: http://github.com/ipazc/pyzip
Author: Iván de Paz Centeno
Author-email: ipazc@unileon.es
License: MIT
Keywords: pyzip dict zip file zipfile memory in-memory
Platform: UNKNOWN
Classifier: Environment :: Console
Classifier: Intended Audience :: Developers
Classifier: Intended Audience :: Education
Classifier: Intended Audience :: Science/Research
Classifier: Natural Language :: English
Classifier: Programming Language :: Python :: 3.4
Classifier: Programming Language :: Python :: 3.5
Classifier: Programming Language :: Python :: 3.6
Classifier: Programming Language :: Python :: 3.7
License-File: LICENSE
License-File: AUTHORS
